Workbook

Sheet Start here
B2: Amount review — checking our largest records against the source
B3: Built 24 September 2026 from the database as loaded 2026-08-31. 213 records: 65 suspects (A), 135 large (B), 13 institution top-fives (C).
B5: What this is for
B6: Our two biggest amount errors so far (IDB Invest's group figure, AfDB's programme envelope) were found by accident. This queue checks the records that carry the most dollars, so the next one is found on purpose. The 200 largest records alone are about an eighth of every dollar in the tracker.
B7: Each check takes one to three minutes. At five a day, priority A takes about 13 days and the whole queue about 43. Priority A is where the errors should be; the rest is confirmation.
B9: Step by step
B10: 1. Open the 'Queue' tab. Work top to bottom: it is already sorted, suspects first, then by size.
B11: 2. Find the first row with an empty yellow 'Verdict' cell.
B12: 3. Read the grey cells: who, what, OUR amount in the source's own currency, and the 'Already known' note if there is one.
B13: 4. Click the link in 'Source' ('Open page', or a web search for EBRD and some Proparco records). Use the 'Institution guide' tab to find where that institution puts the amount, and which differences are normal for it.
B14: 5. Find the institution's OWN commitment for this deal. Not the total project cost, not a programme or facility total, not co-financiers' money.
B15: 6. Fill the yellow cells: pick a Verdict from the dropdown; type the amount the page shows, in the page's currency, as a plain number (250000000, not '250m'); the currency; the words the page uses for it; and today's date (Ctrl+; types it).
... B37: The 'Progress' tab counts what you've done.

Sheet Queue
A1: # | B1: Review ID | C1: Priority | D1: Why it's here | E1: Institution | F1: Project name | G1: Country | H1: Year | I1: Our amount (source currency) | J1: Currency | K1: Our amount (USD m) | L1: Rank within institution | M1: Already known | N1: Source | O1: Verdict | P1: Amount on page | Q1: Page currency | R1: What the page calls it | S1: Notes | T1: Date reviewed | U1: Source URL (key) | V1: Approval date (key) | W1: Exact name (key)
A2: 1 | B2: AR-001 | C2: A | D2: trade-finance line; IFC 'World Region' record of USD 500m or more | E2: IFC | F2: Global Trade Finance Program (GTFP) | G2: Regional — Global | H2: 2004 | I2: 7000000000 | J2: USD | K2: 7000 | L2: 1 | M2: IFC's trade programmes stamp their whole envelope on partner records. Since 24 Sep 2026 the loader blanks it wherever several World Region records share one (GSCF, GTSF), but a LONE World Region record keeps its amount as the programme's own. Check whether this is the programme itself or one partner bank. Trade lines revolve: check whether the figure is a LIMIT (one commitment) or a running total of trade covered over the years. | N2: =HYPERLINK("https://disclosures.ifc.org/project-detail/SPI/23898/global-trade-finance-program-(gtfp)","Open page") | U2: https://disclosures.ifc.org/project-detail/SPI/23898/global-trade-finance-program-(gtfp) | V2: 2004-11-11 | W2: Global Trade Finance Program (GTFP)
A3: 2 | B3: AR-002 | C3: A | D3: trade-finance line | E3: EBRD | F3: Regional TFP: National Bank Of Egypt | G3: Egypt | H3: 2014 | I3: 3.4158555e+09 | J3: EUR | K3: 4537.9674 | L3: 1 | M3: Trade lines revolve: check whether the figure is a LIMIT (one commitment) or a running total of trade covered over the years. Our figure is EBRD's 'Net Cumulative Bank Investment'. | N3: =HYPERLINK("https://www.google.com/search?q=site%3Aebrd.com%2Fhome%2Fwork-with-us%2Fprojects%2Fpsd+Regional+TFP%3A+National+Bank+Of+Egypt","Search EBRD") | U3: https://www.ebrd.com/content/dam/ebrd_dxp/assets/pdfs/publications/ebrd-investments-1991-2025.xlsx | V3: 2014-02-19 | W3: Regional TFP: National Bank Of Egypt
A4: 3 | B4: AR-003 | C4: A | D4: trade-finance line | E4: EBRD | F4: Regional TFP: AikBank | G4: Serbia | H4: 2011 | I4: 1.8260238e+09 | J4: EUR | K4: 2541.7429 | L4: 2 | M4: Trade lines revolve: check whether the figure is a LIMIT (one commitment) or a running total of trade covered over the years. Our figure is EBRD's 'Net Cumulative Bank Investment'. | N4: =HYPERLINK("https://www.google.com/search?q=site%3Aebrd.com%2Fhome%2Fwork-with-us%2Fprojects%2Fpsd+Regional+TFP%3A+AikBank","Search EBRD") | U4: https://www.ebrd.com/content/dam/ebrd_dxp/assets/pdfs/publications/ebrd-investments-1991-2025.xlsx | V4: 2011-02-14 | W4: Regional TFP: AikBank
A5: 4 | B5: AR-004 | C5: A | D5: trade-finance line | E5: EBRD | F5: Regional TFP: BMCE Banque Marocaine pour le Commerce Exterie | G5: Morocco | H5: 2013 | I5: 1.555993e+09 | J5: EUR | K5: 2066.5423 | L5: 3 | M5: Trade lines revolve: check whether the figure is a LIMIT (one commitment) or a running total of trade covered over the years. Our figure is EBRD's 'Net Cumulative Bank Investment'. | N5: =HYPERLINK("https://www.google.com/search?q=site%3Aebrd.com%2Fhome%2Fwork-with-us%2Fprojects%2Fpsd+Regional+TFP%3A+BMCE+Banque+Marocaine+pour+le+Commerce+Exterie","Search EBRD") | U5: https://www.ebrd.com/content/dam/ebrd_dxp/assets/pdfs/publications/ebrd-investments-1991-2025.xlsx | V5: 2013-03-07 | W5: Regional TFP: BMCE Banque Marocaine pour le Commerce Exterie
A6: 5 | B6: AR-005 | C6: A | D6: trade-finance line | E6: EBRD | F6: Regional TFP: Export Import Bank of Ukraine (UkrExIm) | G6: Ukraine | H6: 2007 | I6: 1.5069439e+09 | J6: EUR | K6: 2065.2335 | L6: 4 | M6: Trade lines revolve: check whether the figure is a LIMIT (one commitment) or a running total of trade covered over the years. Our figure is EBRD's 'Net Cumulative Bank Investment'. | N6: =HYPERLINK("https://www.google.com/search?q=site%3Aebrd.com%2Fhome%2Fwork-with-us%2Fprojects%2Fpsd+Regional+TFP%3A+Export+Import+Bank+of+Ukraine+%28UkrExIm%29","Search EBRD") | U6: https://www.ebrd.com/content/dam/ebrd_dxp/assets/pdfs/publications/ebrd-investments-1991-2025.xlsx | V6: 2007-05-20 | W6: Regional TFP: Export Import Bank of Ukraine (UkrExIm)
A7: 6 | B7: AR-006 | C7: A | D7: trade-finance line | E7: EBRD | F7: Regional TFP: Banque Misr | G7: Egypt | H7: 2018 | I7: 1.488434e+09 | J7: EUR | K7: 1757.7736 | L7: 5 | M7: Trade lines revolve: check whether the figure is a LIMIT (one commitment) or a running total of trade covered over the years. Our figure is EBRD's 'Net Cumulative Bank Investment'. | N7: =HYPERLINK("https://www.google.com/search?q=site%3Aebrd.com%2Fhome%2Fwork-with-us%2Fprojects%2Fpsd+Regional+TFP%3A+Banque+Misr","Search EBRD") | U7: https://www.ebrd.com/content/dam/ebrd_dxp/assets/pdfs/publications/ebrd-investments-1991-2025.xlsx | V7: 2018-09-26 | W7: Regional TFP: Banque Misr
A8: 7 | B8: AR-007 | C8: A | D8: trade-finance line | E8: IDB Invest | F8: Banco de Reservas - TFFP | G8: Dominican Republic | H8: 2009 | I8: 1605000000 | J8: USD | K8: 1605 | L8: 1 | M8: Trade lines revolve: check whether the figure is a LIMIT (one commitment) or a running total of trade covered over the years. | N8: =HYPERLINK("https://idbinvest.org/en/projects/banco-de-reservas-tffp","Open page") | U8: https://idbinvest.org/en/projects/banco-de-reservas-tffp | V8: 2009-03-24 | W8: Banco de Reservas - TFFP
A9: 8 | B9: AR-008 | C9: A | D9: trade-finance line | E9: EBRD | F9: Regional TFP: Promsvyazbank | G9: Russia | H9: 2004 | I9: 1.2389867e+09 | J9: EUR | K9: 1541.178 | L9: 6 | M9: Trade lines revolve: check whether the figure is a LIMIT (one commitment) or a running total of trade covered over the years. Our figure is EBRD's 'Net Cumulative Bank Investment'. | N9: =HYPERLINK("https://www.google.com/search?q=site%3Aebrd.com%2Fhome%2Fwork-with-us%2Fprojects%2Fpsd+Regional+TFP%3A+Promsvyazbank","Search EBRD") | U9: https://www.ebrd.com/content/dam/ebrd_dxp/assets/pdfs/publications/ebrd-investments-1991-2025.xlsx | V9: 2004-11-12 | W9: Regional TFP: Promsvyazbank
A10: 9 | B10: AR-009 | C10: A | D10: trade-finance line; IFC 'World Region' record of USD 500m or more | E10: IFC | F10: GTFP IV | G10: Regional — Global | H10: 2008 | I10: 1500000000 | J10: USD | K10: 1500 | L10: 2 | M10: IFC's trade programmes stamp their whole envelope on partner records. Since 24 Sep 2026 the loader blanks it wherever several World Region records share one (GSCF, GTSF), but a LONE World Region record keeps its amount as the programme's own. Check whether this is the programme itself or one partner bank. Trade lines revolve: check whether the figure is a LIMIT (one commitment) or a running total of trade covered over the years. | N10: =HYPERLINK("https://disclosures.ifc.org/project-detail/SPI/27839/gtfp-iv","Open page") | U10: https://disclosures.ifc.org/project-detail/SPI/27839/gtfp-iv | V10: 2008-12-18 | W10: GTFP IV
A11: 10 | B11: AR-010 | C11: A | D11: trade-finance line | E11: EBRD | F11: Regional TFP: Ukrgasbank | G11: Ukraine | H11: 2019 | I11: 1.2800839e+09 | J11: EUR | K11: 1433.022 | L11: 7 | M11: Trade lines revolve: check whether the figure is a LIMIT (one commitment) or a running total of trade covered over the years. Our figure is EBRD's 'Net Cumulative Bank Investment'. | N11: =HYPERLINK("https://www.google.com/search?q=site%3Aebrd.com%2Fhome%2Fwork-with-us%2Fprojects%2Fpsd+Regional+TFP%3A+Ukrgasbank","Search EBRD") | U11: https://www.ebrd.com/content/dam/ebrd_dxp/assets/pdfs/publications/ebrd-investments-1991-2025.xlsx | V11: 2019-07-04 | W11: Regional TFP: Ukrgasbank
A12: 11 | B12: AR-011 | C12: A | D12: trade-finance line | E12: EBRD | F12: Regional TFP: Raiffeisen Bank Ukraine | G12: Ukraine | H12: 2003 | I12: 1.1718922e+09 | J12: EUR | K12: 1325.5976 | L12: 8 | M12: Trade lines revolve: check whether the figure is a LIMIT (one commitment) or a running total of trade covered over the years. Our figure is EBRD's 'Net Cumulative Bank Investment'. | N12: =HYPERLINK("https://www.google.com/search?q=site%3Aebrd.com%2Fhome%2Fwork-with-us%2Fprojects%2Fpsd+Regional+TFP%3A+Raiffeisen+Bank+Ukraine","Search EBRD") | U12: https://www.ebrd.com/content/dam/ebrd_dxp/assets/pdfs/publications/ebrd-investments-1991-2025.xlsx | V12: 2003-05-27 | W12: Regional TFP: Raiffeisen Bank Ukraine
A13: 12 | B13: AR-012 | C13: A | D13: trade-finance line | E13: EBRD | F13: Regional TFP: National Bank of Greece | G13: Greece | H13: 2016 | I13: 9.6995795e+08 | J13: EUR | K13: 1073.6494 | L13: 9 | M13: Trade lines revolve: check whether the figure is a LIMIT (one commitment) or a running total of trade covered over the years. Our figure is EBRD's 'Net Cumulative Bank Investment'. | N13: =HYPERLINK("https://www.google.com/search?q=site%3Aebrd.com%2Fhome%2Fwork-with-us%2Fprojects%2Fpsd+Regional+TFP%3A+National+Bank+of+Greece","Search EBRD") | U13: https://www.ebrd.com/content/dam/ebrd_dxp/assets/pdfs/publications/ebrd-investments-1991-2025.xlsx | V13: 2016-03-01 | W13: Regional TFP: National Bank of Greece
A14: 13 | B14: AR-013 | C14: A | D14: trade-finance line | E14: EBRD | F14: Regional TFP: TBC Bank (guarantee & pre-export) | G14: Georgia | H14: 1999 | I14: 9.8311367e+08 | J14: EUR | K14: 1047.779 | L14: 10 | M14: Trade lines revolve: check whether the figure is a LIMIT (one commitment) or a running total of trade covered over the years. Our figure is EBRD's 'Net Cumulative Bank Investment'. | N14: =HYPERLINK("https://www.google.com/search?q=site%3Aebrd.com%2Fhome%2Fwork-with-us%2Fprojects%2Fpsd+Regional+TFP%3A+TBC+Bank+%28guarantee+%26+pre-export%29","Search EBRD") | U14: https://www.ebrd.com/content/dam/ebrd_dxp/assets/pdfs/publications/ebrd-investments-1991-2025.xlsx | V14: 1999-08-17 | W14: Regional TFP: TBC Bank (guarantee & pre-export)
A15: 14 | B15: AR-014 | C15: A | D15: IFC 'World Region' record of USD 500m or more | E15: IFC | F15: Bank Recap Fund | G15: Regional — Global | H15: 2008 | I15: 1003000000 | J15: USD | K15: 1003 | L15: 3 | M15: IFC's trade programmes stamp their whole envelope on partner records. Since 24 Sep 2026 the loader blanks it wherever several World Region records share one (GSCF, GTSF), but a LONE World Region record keeps its amount as the programme's own. Check whether this is the programme itself or one partner bank. | N15: =HYPERLINK("https://disclosures.ifc.org/project-detail/SPI/27832/bank-recap-fund","Open page") | U15: https://disclosures.ifc.org/project-detail/SPI/27832/bank-recap-fund | V15: 2008-12-18 | W15: Bank Recap Fund
A16: 15 | B16: AR-015 | C16: A | D16: trade-finance line | E16: ADB | F16: REG: TRADE FINANCE FACILITATION PROGRAM | G16: Regional — Asia | H16: 2009 | I16: 1000000000 | J16: USD | K16: 1000 | L16: 1 | M16: Trade lines revolve: check whether the figure is a LIMIT (one commitment) or a running total of trade covered over the years. | N16: =HYPERLINK("https://www.adb.org/projects/37909-024/main","Open page") | U16: https://www.adb.org/projects/37909-024/main | V16: 2009-03-31 | W16: REG: TRADE FINANCE FACILITATION PROGRAM
A17: 16 | B17: AR-016 | C17: A | D17: IFC 'World Region' record of USD 500m or more | E17: IFC | F17: Global Trade Liquidity Program | G17: Regional — Global | H17: 2009 | I17: 1000000000 | J17: USD | K17: 1000 | L17: 4 | M17: IFC's trade programmes stamp their whole envelope on partner records. Since 24 Sep 2026 the loader blanks it wherever several World Region records share one (GSCF, GTSF), but a LONE World Region record keeps its amount as the programme's own. Check whether this is the programme itself or one partner bank. | N17: =HYPERLINK("https://disclosures.ifc.org/project-detail/SPI/28088/global-trade-liquidity-program","Open page") | U17: https://disclosures.ifc.org/project-detail/SPI/28088/global-trade-liquidity-program | V17: 2009-03-31 | W17: Global Trade Liquidity Program
A18: 17 | B18: AR-017 | C18: A | D18: trade-finance line; IFC 'World Region' record of USD 500m or more | E18: IFC | F18: TECF Citi | G18: Regional — Global | H18: 2024 | I18: 1000000000 | J18: USD | K18: 1000 | L18: 5 | M18: IFC's trade programmes stamp their whole envelope on partner records. Since 24 Sep 2026 the loader blanks it wherever several World Region records share one (GSCF, GTSF), but a LONE World Region record keeps its amount as the programme's own. Check whether this is the programme itself or one partner bank. Trade lines revolve: check whether the figure is a LIMIT (one commitment) or a running total of trade covered over the years. | N18: =HYPERLINK("https://disclosures.ifc.org/project-detail/SII/49729/tecf-citi","Open page") | U18: https://disclosures.ifc.org/project-detail/SII/49729/tecf-citi | V18: 2024-11-11 | W18: TECF Citi
A19: 18 | B19: AR-018 | C19: A | D19: trade-finance line | E19: EBRD | F19: Regional TFP: ABC Factors | G19: Greece | H19: 2020 | I19: 860000000 | J19: EUR | K19: 982.28856 | L19: 11 | M19: Trade lines revolve: check whether the figure is a LIMIT (one commitment) or a running total of trade covered over the years. Our figure is EBRD's 'Net Cumulative Bank Investment'. | N19: =HYPERLINK("https://www.google.com/search?q=site%3Aebrd.com%2Fhome%2Fwork-with-us%2Fprojects%2Fpsd+Regional+TFP%3A+ABC+Factors","Search EBRD") | U19: https://www.ebrd.com/content/dam/ebrd_dxp/assets/pdfs/publications/ebrd-investments-1991-2025.xlsx | V19: 2020-11-30 | W19: Regional TFP: ABC Factors
A20: 19 | B20: AR-019 | C20: A | D20: trade-finance line | E20: EBRD | F20: Regional TFP: Alternatifbank | G20: Türkiye | H20: 2016 | I20: 8.6044808e+08 | J20: EUR | K20: 952.43257 | L20: 12 | M20: Trade lines revolve: check whether the figure is a LIMIT (one commitment) or a running total of trade covered over the years. Our figure is EBRD's 'Net Cumulative Bank Investment'. | N20: =HYPERLINK("https://www.google.com/search?q=site%3Aebrd.com%2Fhome%2Fwork-with-us%2Fprojects%2Fpsd+Regional+TFP%3A+Alternatifbank","Search EBRD") | U20: https://www.ebrd.com/content/dam/ebrd_dxp/assets/pdfs/publications/ebrd-investments-1991-2025.xlsx | V20: 2016-12-01 | W20: Regional TFP: Alternatifbank
A21: 20 | B21: AR-020 | C21: A | D21: trade-finance line | E21: EBRD | F21: Regional TFP: Bank of Georgia (Guarantee & Pre-export) | G21: Georgia | H21: 1999 | I21: 8.1880591e+08 | J21: EUR | K21: 872.66369 | L21: 13 | M21: Trade lines revolve: check whether the figure is a LIMIT (one commitment) or a running total of trade covered over the years. Our figure is EBRD's 'Net Cumulative Bank Investment'. | N21: =HYPERLINK("https://www.google.com/search?q=site%3Aebrd.com%2Fhome%2Fwork-with-us%2Fprojects%2Fpsd+Regional+TFP%3A+Bank+of+Georgia+%28Guarantee+%26+Pre-export%29","Search EBRD") | U21: https://www.ebrd.com/content/dam/ebrd_dxp/assets/pdfs/publications/ebrd-investments-1991-2025.xlsx | V21: 1999-07-29 | W21: Regional TFP: Bank of Georgia (Guarantee & Pre-export)
A22: 21 | B22: AR-021 | C22: A | D22: trade-finance line | E22: EBRD | F22: Regional TFP: Vakiflar Bankasi TAO | G22: Türkiye | H22: 2011 | I22: 6.1049468e+08 | J22: EUR | K22: 849.78112 | L22: 14 | M22: Trade lines revolve: check whether the figure is a LIMIT (one commitment) or a running total of trade covered over the years. Our figure is EBRD's 'Net Cumulative Bank Investment'. | N22: =HYPERLINK("https://www.google.com/search?q=site%3Aebrd.com%2Fhome%2Fwork-with-us%2Fprojects%2Fpsd+Regional+TFP%3A+Vakiflar+Bankasi+TAO","Search EBRD") | U22: https://www.ebrd.com/content/dam/ebrd_dxp/assets/pdfs/publications/ebrd-investments-1991-2025.xlsx | V22: 2011-01-26 | W22: Regional TFP: Vakiflar Bankasi TAO
A23: 22 | B23: AR-022 | C23: A | D23: trade-finance line | E23: IDB Invest | F23: Banco Industrial - TFFP | G23: Guatemala | H23: 2008 | I23: 848544000 | J23: USD | K23: 848.544 | L23: 2 | M23: Trade lines revolve: check whether the figure is a LIMIT (one commitment) or a running total of trade covered over the years. | N23: =HYPERLINK("https://idbinvest.org/en/projects/banco-industrial-tffp","Open page") | U23: https://idbinvest.org/en/projects/banco-industrial-tffp | V23: 2008-07-28 | W23: Banco Industrial - TFFP
A24: 23 | B24: AR-023 | C24: A | D24: trade-finance line | E24: EBRD | F24: Regional TFP: Alpha Bank | G24: Greece | H24: 2016 | I24: 7.5374195e+08 | J24: EUR | K24: 834.31923 | L24: 15 | M24: Trade lines revolve: check whether the figure is a LIMIT (one commitment) or a running total of trade covered over the years. Our figure is EBRD's 'Net Cumulative Bank Investment'. | N24: =HYPERLINK("https://www.google.com/search?q=site%3Aebrd.com%2Fhome%2Fwork-with-us%2Fprojects%2Fpsd+Regional+TFP%3A+Alpha+Bank","Search EBRD") | U24: https://www.ebrd.com/content/dam/ebrd_dxp/assets/pdfs/publications/ebrd-investments-1991-2025.xlsx | V24: 2016-07-22 | W24: Regional TFP: Alpha Bank
A25: 24 | B25: AR-024 | C25: A | D25: trade-finance line; IFC 'World Region' record of USD 500m or more | E25: IFC | F25: GTLP CITI VI | G25: Regional — Global | H25: 2024 | I25: 800000000 | J25: USD | K25: 800 | L25: 6 | M25: IFC's trade programmes stamp their whole envelope on partner records. Since 24 Sep 2026 the loader blanks it wherever several World Region records share one (GSCF, GTSF), but a LONE World Region record keeps its amount as the programme's own. Check whether this is the programme itself or one partner bank. Trade lines revolve: check whether the figure is a LIMIT (one commitment) or a running total of trade covered over the years. | N25: =HYPERLINK("https://disclosures.ifc.org/project-detail/SII/49391/gtlp-citi-vi","Open page") | U25: https://disclosures.ifc.org/project-detail/SII/49391/gtlp-citi-vi | V25: 2024-07-16 | W25: GTLP CITI VI
A26: 25 | B26: AR-025 | C26: A | D26: trade-finance line | E26: IDB Invest | F26: Banco Santander Brasil S.A. - TFFP | G26: Brazil | H26: 2013 | I26: 777842000 | J26: USD | K26: 777.842 | L26: 3 | M26: Trade lines revolve: check whether the figure is a LIMIT (one commitment) or a running total of trade covered over the years. | N26: =HYPERLINK("https://idbinvest.org/en/projects/banco-santander-brasil-sa-tffp","Open page") | U26: https://idbinvest.org/en/projects/banco-santander-brasil-sa-tffp | V26: 2013-11-25 | W26: Banco Santander Brasil S.A. - TFFP
A27: 26 | B27: AR-026 | C27: A | D27: trade-finance line | E27: EBRD | F27: Regional TFP: Banque de Tunisie | G27: Tunisia | H27: 2018 | I27: 6.3417372e+08 | J27: EUR | K27: 748.93062 | L27: 18 | M27: Trade lines revolve: check whether the figure is a LIMIT (one commitment) or a running total of trade covered over the years. Our figure is EBRD's 'Net Cumulative Bank Investment'. | N27: =HYPERLINK("https://www.google.com/search?q=site%3Aebrd.com%2Fhome%2Fwork-with-us%2Fprojects%2Fpsd+Regional+TFP%3A+Banque+de+Tunisie","Search EBRD") | U27: https://www.ebrd.com/content/dam/ebrd_dxp/assets/pdfs/publications/ebrd-investments-1991-2025.xlsx | V27: 2018-06-11 | W27: Regional TFP: Banque de Tunisie
A28: 27 | B28: AR-027 | C28: A | D28: trade-finance line | E28: EBRD | F28: Regional TFP: QNB Finansbank | G28: Türkiye | H28: 2020 | I28: 6.5101141e+08 | J28: EUR | K28: 743.58263 | L28: 19 | M28: Trade lines revolve: check whether the figure is a LIMIT (one commitment) or a running total of trade covered over the years. Our figure is EBRD's 'Net Cumulative Bank Investment'. | N28: =HYPERLINK("https://www.google.com/search?q=site%3Aebrd.com%2Fhome%2Fwork-with-us%2Fprojects%2Fpsd+Regional+TFP%3A+QNB+Finansbank","Search EBRD") | U28: https://www.ebrd.com/content/dam/ebrd_dxp/assets/pdfs/publications/ebrd-investments-1991-2025.xlsx | V28: 2020-06-11 | W28: Regional TFP: QNB Finansbank
A29: 28 | B29: AR-028 | C29: A | D29: trade-finance line | E29: IDB Invest | F29: Banco ABC Brasil S.A. - TFFP Line | G29: Brazil | H29: 2020 | I29: 741018000 | J29: USD | K29: 741.018 | L29: 4 | M29: Trade lines revolve: check whether the figure is a LIMIT (one commitment) or a running total of trade covered over the years. | N29: =HYPERLINK("https://idbinvest.org/en/projects/banco-abc-brasil-sa-tffp-line","Open page") | U29: https://idbinvest.org/en/projects/banco-abc-brasil-sa-tffp-line | V29: 2020-05-29 | W29: Banco ABC Brasil S.A. - TFFP Line
A30: 29 | B30: AR-029 | C30: A | D30: trade-finance line | E30: EBRD | F30: Regional TFP: Piraeus Bank S.A. | G30: Greece | H30: 2016 | I30: 5.9758718e+08 | J30: EUR | K30: 661.47104 | L30: 20 | M30: Trade lines revolve: check whether the figure is a LIMIT (one commitment) or a running total of trade covered over the years. Our figure is EBRD's 'Net Cumulative Bank Investment'. | N30: =HYPERLINK("https://www.google.com/search?q=site%3Aebrd.com%2Fhome%2Fwork-with-us%2Fprojects%2Fpsd+Regional+TFP%3A+Piraeus+Bank+S.A.","Search EBRD") | U30: https://www.ebrd.com/content/dam/ebrd_dxp/assets/pdfs/publications/ebrd-investments-1991-2025.xlsx | V30: 2016-10-03 | W30: Regional TFP: Piraeus Bank S.A.
A31: 30 | B31: AR-030 | C31: A | D31: trade-finance line; IFC 'World Region' record of USD 500m or more | E31: IFC | F31: GTFP- IDA PSW | G31: Regional — Global | H31: 2020 | I31: 650000000 | J31: USD | K31: 650 | L31: 7 | M31: IFC's trade programmes stamp their whole envelope on partner records. Since 24 Sep 2026 the loader blanks it wherever several World Region records share one (GSCF, GTSF), but a LONE World Region record keeps its amount as the programme's own. Check whether this is the programme itself or one partner bank. Trade lines revolve: check whether the figure is a LIMIT (one commitment) or a running total of trade covered over the years. | N31: =HYPERLINK("https://disclosures.ifc.org/project-detail/SII/44011/gtfp--ida-psw","Open page") | U31: https://disclosures.ifc.org/project-detail/SII/44011/gtfp--ida-psw | V31: 2020-04-24 | W31: GTFP- IDA PSW
A32: 31 | B32: AR-031 | C32: A | D32: trade-finance line | E32: EBRD | F32: Regional TFP: UzPSB | G32: Uzbekistan | H32: 2019 | I32: 5.7049262e+08 | J32: EUR | K32: 638.65223 | L32: 21 | M32: Trade lines revolve: check whether the figure is a LIMIT (one commitment) or a running total of trade covered over the years. Our figure is EBRD's 'Net Cumulative Bank Investment'. | N32: =HYPERLINK("https://www.google.com/search?q=site%3Aebrd.com%2Fhome%2Fwork-with-us%2Fprojects%2Fpsd+Regional+TFP%3A+UzPSB","Search EBRD") | U32: https://www.ebrd.com/content/dam/ebrd_dxp/assets/pdfs/publications/ebrd-investments-1991-2025.xlsx | V32: 2019-03-21 | W32: Regional TFP: UzPSB
A33: 32 | B33: AR-032 | C33: A | D33: trade-finance line | E33: EBRD | F33: Regional TFP: JSCB OTP Bank, Ukraine | G33: Ukraine | H33: 2002 | I33: 6.5934429e+08 | J33: EUR | K33: 623.45882 | L33: 22 | M33: Trade lines revolve: check whether the figure is a LIMIT (one commitment) or a running total of trade covered over the years. Our figure is EBRD's 'Net Cumulative Bank Investment'. | N33: =HYPERLINK("https://www.google.com/search?q=site%3Aebrd.com%2Fhome%2Fwork-with-us%2Fprojects%2Fpsd+Regional+TFP%3A+JSCB+OTP+Bank%2C+Ukraine","Search EBRD") | U33: https://www.ebrd.com/content/dam/ebrd_dxp/assets/pdfs/publications/ebrd-investments-1991-2025.xlsx | V33: 2002-10-22 | W33: Regional TFP: JSCB OTP Bank, Ukraine
A34: 33 | B34: AR-033 | C34: A | D34: trade-finance line; IFC 'World Region' record of USD 500m or more | E34: IFC | F34: GTLP Citi III | G34: Regional — Global | H34: 2015 | I34: 600000000 | J34: USD | K34: 600 | L34: 8 | M34: IFC's trade programmes stamp their whole envelope on partner records. Since 24 Sep 2026 the loader blanks it wherever several World Region records share one (GSCF, GTSF), but a LONE World Region record keeps its amount as the programme's own. Check whether this is the programme itself or one partner bank. Trade lines revolve: check whether the figure is a LIMIT (one commitment) or a running total of trade covered over the years. | N34: =HYPERLINK("https://disclosures.ifc.org/project-detail/SII/36386/gtlp-citi-iii","Open page") | U34: https://disclosures.ifc.org/project-detail/SII/36386/gtlp-citi-iii | V34: 2015-05-15 | W34: GTLP Citi III
A35: 34 | B35: AR-034 | C35: A | D35: trade-finance line; IFC 'World Region' record of USD 500m or more | E35: IFC | F35: GTLP Citi IV | G35: Regional — Global | H35: 2018 | I35: 600000000 | J35: USD | K35: 600 | L35: 9 | M35: IFC's trade programmes stamp their whole envelope on partner records. Since 24 Sep 2026 the loader blanks it wherever several World Region records share one (GSCF, GTSF), but a LONE World Region record keeps its amount as the programme's own. Check whether this is the programme itself or one partner bank. Trade lines revolve: check whether the figure is a LIMIT (one commitment) or a running total of trade covered over the years. | N35: =HYPERLINK("https://disclosures.ifc.org/project-detail/SII/40688/gtlp-citi-iv","Open page") | U35: https://disclosures.ifc.org/project-detail/SII/40688/gtlp-citi-iv | V35: 2018-05-31 | W35: GTLP Citi IV
A36: 35 | B36: AR-035 | C36: A | D36: trade-finance line; IFC 'World Region' record of USD 500m or more | E36: IFC | F36: GTLP CITI V | G36: Regional — Global | I36: 600000000 | J36: USD | K36: 600 | L36: 10 | M36: IFC's trade programmes stamp their whole envelope on partner records. Since 24 Sep 2026 the loader blanks it wherever several World Region records share one (GSCF, GTSF), but a LONE World Region record keeps its amount as the programme's own. Check whether this is the programme itself or one partner bank. Trade lines revolve: check whether the figure is a LIMIT (one commitment) or a running total of trade covered over the years. | N36: =HYPERLINK("https://disclosures.ifc.org/project-detail/SII/45495/gtlp-citi-v","Open page") | U36: https://disclosures.ifc.org/project-detail/SII/45495/gtlp-citi-v | W36: GTLP CITI V
A37: 36 | B37: AR-036 | C37: A | D37: trade-finance line | E37: EBRD | F37: Regional TFP: Vneshtorgbank (Guarantee & Pre-export) | G37: Russia | H37: 1999 | I37: 5.4885691e+08 | J37: EUR | K37: 584.95852 | L37: 24 | M37: Trade lines revolve: check whether the figure is a LIMIT (one commitment) or a running total of trade covered over the years. Our figure is EBRD's 'Net Cumulative Bank Investment'. | N37: =HYPERLINK("https://www.google.com/search?q=site%3Aebrd.com%2Fhome%2Fwork-with-us%2Fprojects%2Fpsd+Regional+TFP%3A+Vneshtorgbank+%28Guarantee+%26+Pre-export%29","Search EBRD") | U37: https://www.ebrd.com/content/dam/ebrd_dxp/assets/pdfs/publications/ebrd-investments-1991-2025.xlsx | V37: 1999-06-10 | W37: Regional TFP: Vneshtorgbank (Guarantee & Pre-export)
A38: 37 | B38: AR-037 | C38: A | D38: trade-finance line | E38: EBRD | F38: Regional TFP: Burgan Bank AS | G38: Türkiye | H38: 2017 | I38: 5.0401326e+08 | J38: EUR | K38: 569.37421 | L38: 25 | M38: Trade lines revolve: check whether the figure is a LIMIT (one commitment) or a running total of trade covered over the years. Our figure is EBRD's 'Net Cumulative Bank Investment'. | N38: =HYPERLINK("https://www.google.com/search?q=site%3Aebrd.com%2Fhome%2Fwork-with-us%2Fprojects%2Fpsd+Regional+TFP%3A+Burgan+Bank+AS","Search EBRD") | U38: https://www.ebrd.com/content/dam/ebrd_dxp/assets/pdfs/publications/ebrd-investments-1991-2025.xlsx | V38: 2017-02-09 | W38: Regional TFP: Burgan Bank AS
A39: 38 | B39: AR-038 | C39: A | D39: trade-finance line | E39: EBRD | F39: Regional TFP: Ameria Bank CJSC | G39: Armenia | H39: 2010 | I39: 4.0013057e+08 | J39: EUR | K39: 530.45989 | L39: 29 | M39: Trade lines revolve: check whether the figure is a LIMIT (one commitment) or a running total of trade covered over the years. Our figure is EBRD's 'Net Cumulative Bank Investment'. | N39: =HYPERLINK("https://www.google.com/search?q=site%3Aebrd.com%2Fhome%2Fwork-with-us%2Fprojects%2Fpsd+Regional+TFP%3A+Ameria+Bank+CJSC","Search EBRD") | U39: https://www.ebrd.com/content/dam/ebrd_dxp/assets/pdfs/publications/ebrd-investments-1991-2025.xlsx | V39: 2010-05-15 | W39: Regional TFP: Ameria Bank CJSC
A40: 39 | B40: AR-039 | C40: A | D40: trade-finance line | E40: EBRD | F40: Regional TFP : Bank al Etihad | G40: Jordan | H40: 2014 | I40: 3.9439071e+08 | J40: EUR | K40: 523.94846 | L40: 30 | M40: Trade lines revolve: check whether the figure is a LIMIT (one commitment) or a running total of trade covered over the years. Our figure is EBRD's 'Net Cumulative Bank Investment'. | N40: =HYPERLINK("https://www.google.com/search?q=site%3Aebrd.com%2Fhome%2Fwork-with-us%2Fprojects%2Fpsd+Regional+TFP+%3A+Bank+al+Etihad","Search EBRD") | U40: https://www.ebrd.com/content/dam/ebrd_dxp/assets/pdfs/publications/ebrd-investments-1991-2025.xlsx | V40: 2014-12-18 | W40: Regional TFP : Bank al Etihad
A41: 40 | B41: AR-040 | C41: A | D41: trade-finance line | E41: EBRD | F41: Regional TFP:Commercial International Bk | G41: Egypt | H41: 2014 | I41: 3.7973422e+08 | J41: EUR | K41: 504.47729 | L41: 32 | M41: Trade lines revolve: check whether the figure is a LIMIT (one commitment) or a running total of trade covered over the years. Our figure is EBRD's 'Net Cumulative Bank Investment'. | N41: =HYPERLINK("https://www.google.com/search?q=site%3Aebrd.com%2Fhome%2Fwork-with-us%2Fprojects%2Fpsd+Regional+TFP%3ACommercial+International+Bk","Search EBRD") | U41: https://www.ebrd.com/content/dam/ebrd_dxp/assets/pdfs/publications/ebrd-investments-1991-2025.xlsx | V41: 2014-12-11 | W41: Regional TFP:Commercial International Bk
A42: 41 | B42: AR-041 | C42: A | D42: trade-finance line | E42: IFC | F42: GTLP SMBC LAC | G42: Regional — Latin America & Caribbean | H42: 2026 | I42: 502500000 | J42: USD | K42: 502.5 | L42: 11 | M42: Trade lines revolve: check whether the figure is a LIMIT (one commitment) or a running total of trade covered over the years. | N42: =HYPERLINK("https://disclosures.ifc.org/project-detail/SII/51524/gtlp-smbc-lac","Open page") | U42: https://disclosures.ifc.org/project-detail/SII/51524/gtlp-smbc-lac | V42: 2026-03-31 | W42: GTLP SMBC LAC
A43: 42 | B43: AR-042 | C43: A | D43: trade-finance line | E43: IDB Invest | F43: Banco Interamericano de Finanzas - TFFP | G43: Peru | H43: 2007 | I43: 500500000 | J43: USD | K43: 500.5 | L43: 5 | M43: Trade lines revolve: check whether the figure is a LIMIT (one commitment) or a running total of trade covered over the years. | N43: =HYPERLINK("https://idbinvest.org/en/projects/banco-interamericano-de-finanzas-tffp","Open page") | U43: https://idbinvest.org/en/projects/banco-interamericano-de-finanzas-tffp | V43: 2007-03-14 | W43: Banco Interamericano de Finanzas - TFFP
A44: 43 | B44: AR-043 | C44: A | D44: trade-finance line; IFC 'World Region' record of USD 500m or more | E44: IFC | F44: GTFP II | G44: Regional — Global | H44: 2007 | I44: 500000000 | J44: USD | K44: 500 | L44: 12 | M44: IFC's trade programmes stamp their whole envelope on partner records. Since 24 Sep 2026 the loader blanks it wherever several World Region records share one (GSCF, GTSF), but a LONE World Region record keeps its amount as the programme's own. Check whether this is the programme itself or one partner bank. Trade lines revolve: check whether the figure is a LIMIT (one commitment) or a running total of trade covered over the years. | N44: =HYPERLINK("https://disclosures.ifc.org/project-detail/SPI/25667/gtfp-ii","Open page") | U44: https://disclosures.ifc.org/project-detail/SPI/25667/gtfp-ii | V44: 2007-01-11 | W44: GTFP II
A45: 44 | B45: AR-044 | C45: A | D45: trade-finance line; IFC 'World Region' record of USD 500m or more | E45: IFC | F45: GTFP III | G45: Regional — Global | H45: 2008 | I45: 500000000 | J45: USD | K45: 500 | L45: 13 | M45: IFC's trade programmes stamp their whole envelope on partner records. Since 24 Sep 2026 the loader blanks it wherever several World Region records share one (GSCF, GTSF), but a LONE World Region record keeps its amount as the programme's own. Check whether this is the programme itself or one partner bank. Trade lines revolve: check whether the figure is a LIMIT (one commitment) or a running total of trade covered over the years. | N45: =HYPERLINK("https://disclosures.ifc.org/project-detail/SPI/27372/gtfp-iii","Open page") | U45: https://disclosures.ifc.org/project-detail/SPI/27372/gtfp-iii | V45: 2008-10-02 | W45: GTFP III
A46: 45 | B46: AR-045 | C46: A | D46: IFC 'World Region' record of USD 500m or more | E46: IFC | F46: DARP Global AGM | G46: Regional — Global | H46: 2016 | I46: 500000000 | J46: USD | K46: 500 | L46: 14 | M46: IFC's trade programmes stamp their whole envelope on partner records. Since 24 Sep 2026 the loader blanks it wherever several World Region records share one (GSCF, GTSF), but a LONE World Region record keeps its amount as the programme's own. Check whether this is the programme itself or one partner bank. | N46: =HYPERLINK("https://disclosures.ifc.org/project-detail/SII/37035/darp-global-agm","Open page") | U46: https://disclosures.ifc.org/project-detail/SII/37035/darp-global-agm | V46: 2016-06-09 | W46: DARP Global AGM
A47: 46 | B47: AR-046 | C47: A | D47: trade-finance line; IFC 'World Region' record of USD 500m or more | E47: IFC | F47: GTLP-SMBC | G47: Regional — Global | H47: 2016 | I47: 500000000 | J47: USD | K47: 500 | L47: 15 | M47: IFC's trade programmes stamp their whole envelope on partner records. Since 24 Sep 2026 the loader blanks it wherever several World Region records share one (GSCF, GTSF), but a LONE World Region record keeps its amount as the programme's own. Check whether this is the programme itself or one partner bank. Trade lines revolve: check whether the figure is a LIMIT (one commitment) or a running total of trade covered over the years. | N47: =HYPERLINK("https://disclosures.ifc.org/project-detail/SII/37978/gtlp-smbc","Open page") | U47: https://disclosures.ifc.org/project-detail/SII/37978/gtlp-smbc | V47: 2016-03-22 | W47: GTLP-SMBC
A48: 47 | B48: AR-047 | C48: A | D48: trade-finance line; IFC 'World Region' record of USD 500m or more | E48: IFC | F48: GTLP SCB III | G48: Regional — Global | H48: 2016 | I48: 500000000 | J48: USD | K48: 500 | L48: 16 | M48: IFC's trade programmes stamp their whole envelope on partner records. Since 24 Sep 2026 the loader blanks it wherever several World Region records share one (GSCF, GTSF), but a LONE World Region record keeps its amount as the programme's own. Check whether this is the programme itself or one partner bank. Trade lines revolve: check whether the figure is a LIMIT (one commitment) or a running total of trade covered over the years. | N48: =HYPERLINK("https://disclosures.ifc.org/project-detail/SII/38705/gtlp-scb-iii","Open page") | U48: https://disclosures.ifc.org/project-detail/SII/38705/gtlp-scb-iii | V48: 2016-11-15 | W48: GTLP SCB III
A49: 48 | B49: AR-048 | C49: A | D49: trade-finance line; IFC 'World Region' record of USD 500m or more | E49: IFC | F49: Standard Chartered Bank Trade Finance Risk Sharing Facility | G49: Regional — Global | H49: 2018 | I49: 500000000 | J49: USD | K49: 500 | L49: 17 | M49: IFC's trade programmes stamp their whole envelope on partner records. Since 24 Sep 2026 the loader blanks it wherever several World Region records share one (GSCF, GTSF), but a LONE World Region record keeps its amount as the programme's own. Check whether this is the programme itself or one partner bank. Trade lines revolve: check whether the figure is a LIMIT (one commitment) or a running total of trade covered over the years. | N49: =HYPERLINK("https://disclosures.ifc.org/project-detail/SII/40541/standard-chartered-bank-trade-finance-risk-sharing-facility","Open page") | U49: https://disclosures.ifc.org/project-detail/SII/40541/standard-chartered-bank-trade-finance-risk-sharing-facility | V49: 2018-10-30 | W49: Standard Chartered Bank Trade Finance Risk Sharing Facility
A50: 49 | B50: AR-049 | C50: A | D50: trade-finance line; IFC 'World Region' record of USD 500m or more | E50: IFC | F50: GTLP SMBC II | G50: Regional — Global | H50: 2019 | I50: 500000000 | J50: USD | K50: 500 | L50: 18 | M50: IFC's trade programmes stamp their whole envelope on partner records. Since 24 Sep 2026 the loader blanks it wherever several World Region records share one (GSCF, GTSF), but a LONE World Region record keeps its amount as the programme's own. Check whether this is the programme itself or one partner bank. Trade lines revolve: check whether the figure is a LIMIT (one commitment) or a running total of trade covered over the years. | N50: =HYPERLINK("https://disclosures.ifc.org/project-detail/SII/42104/gtlp-smbc-ii","Open page") | U50: https://disclosures.ifc.org/project-detail/SII/42104/gtlp-smbc-ii | V50: 2019-05-02 | W50: GTLP SMBC II
A51: 50 | B51: AR-050 | C51: A | D51: trade-finance line; IFC 'World Region' record of USD 500m or more | E51: IFC | F51: GTFP MIGA | G51: Regional — Global | H51: 2021 | I51: 500000000 | J51: USD | K51: 500 | L51: 19 | M51: IFC's trade programmes stamp their whole envelope on partner records. Since 24 Sep 2026 the loader blanks it wherever several World Region records share one (GSCF, GTSF), but a LONE World Region record keeps its amount as the programme's own. Check whether this is the programme itself or one partner bank. Trade lines revolve: check whether the figure is a LIMIT (one commitment) or a running total of trade covered over the years. | N51: =HYPERLINK("https://disclosures.ifc.org/project-detail/SII/45617/gtfp-miga-","Open page") | U51: https://disclosures.ifc.org/project-detail/SII/45617/gtfp-miga- | V51: 2021-05-27 | W51: GTFP MIGA
A52: 51 | B52: AR-051 | C52: A | D52: trade-finance line; IFC 'World Region' record of USD 500m or more | E52: IFC | F52: GTLP SMBC III | G52: Regional — Global | I52: 500000000 | J52: USD | K52: 500 | L52: 20 | M52: IFC's trade programmes stamp their whole envelope on partner records. Since 24 Sep 2026 the loader blanks it wherever several World Region records share one (GSCF, GTSF), but a LONE World Region record keeps its amount as the programme's own. Check whether this is the programme itself or one partner bank. Trade lines revolve: check whether the figure is a LIMIT (one commitment) or a running total of trade covered over the years. | N52: =HYPERLINK("https://disclosures.ifc.org/project-detail/SII/46357/gtlp-smbc-iii","Open page") | U52: https://disclosures.ifc.org/project-detail/SII/46357/gtlp-smbc-iii | W52: GTLP SMBC III
A53: 52 | B53: AR-052 | C53: A | D53: trade-finance line; IFC 'World Region' record of USD 500m or more | E53: IFC | F53: GTLP HSBC Asia | G53: Regional — Global | H53: 2024 | I53: 500000000 | J53: USD | K53: 500 | L53: 23 | M53: IFC's trade programmes stamp their whole envelope on partner records. Since 24 Sep 2026 the loader blanks it wherever several World Region records share one (GSCF, GTSF), but a LONE World Region record keeps its amount as the programme's own. Check whether this is the programme itself or one partner bank. Trade lines revolve: check whether the figure is a LIMIT (one commitment) or a running total of trade covered over the years. | N53: =HYPERLINK("https://disclosures.ifc.org/project-detail/SII/48463/gtlp-hsbc-asia-","Open page") | U53: https://disclosures.ifc.org/project-detail/SII/48463/gtlp-hsbc-asia- | V53: 2024-05-16 | W53: GTLP HSBC Asia
A54: 53 | B54: AR-053 | C54: A | D54: trade-finance line | E54: EBRD | F54: Regional TFP: QNB Al Ahli Bank Egypt | G54: Egypt | H54: 2015 | I54: 4.4086565e+08 | J54: EUR | K54: 489.14617 | L54: 34 | M54: Trade lines revolve: check whether the figure is a LIMIT (one commitment) or a running total of trade covered over the years. Our figure is EBRD's 'Net Cumulative Bank Investment'. | N54: =HYPERLINK("https://www.google.com/search?q=site%3Aebrd.com%2Fhome%2Fwork-with-us%2Fprojects%2Fpsd+Regional+TFP%3A+QNB+Al+Ahli+Bank+Egypt","Search EBRD") | U54: https://www.ebrd.com/content/dam/ebrd_dxp/assets/pdfs/publications/ebrd-investments-1991-2025.xlsx | V54: 2015-07-16 | W54: Regional TFP: QNB Al Ahli Bank Egypt
A55: 54 | B55: AR-054 | C55: A | D55: trade-finance line | E55: EBRD | F55: Regional TFP: Asaka bank | G55: Uzbekistan | H55: 2019 | I55: 4.368454e+08 | J55: EUR | K55: 489.03751 | L55: 35 | M55: Trade lines revolve: check whether the figure is a LIMIT (one commitment) or a running total of trade covered over the years. Our figure is EBRD's 'Net Cumulative Bank Investment'. | N55: =HYPERLINK("https://www.google.com/search?q=site%3Aebrd.com%2Fhome%2Fwork-with-us%2Fprojects%2Fpsd+Regional+TFP%3A+Asaka+bank","Search EBRD") | U55: https://www.ebrd.com/content/dam/ebrd_dxp/assets/pdfs/publications/ebrd-investments-1991-2025.xlsx | V55: 2019-09-04 | W55: Regional TFP: Asaka bank
A56: 55 | B56: AR-055 | C56: A | D56: trade-finance line | E56: EBRD | F56: Regional TFP: Locko Bank | G56: Russia | H56: 2005 | I56: 3.8583943e+08 | J56: EUR | K56: 480.01898 | L56: 37 | M56: Trade lines revolve: check whether the figure is a LIMIT (one commitment) or a running total of trade covered over the years. Our figure is EBRD's 'Net Cumulative Bank Investment'. | N56: =HYPERLINK("https://www.google.com/search?q=site%3Aebrd.com%2Fhome%2Fwork-with-us%2Fprojects%2Fpsd+Regional+TFP%3A+Locko+Bank","Search EBRD") | U56: https://www.ebrd.com/content/dam/ebrd_dxp/assets/pdfs/publications/ebrd-investments-1991-2025.xlsx | V56: 2005-09-23 | W56: Regional TFP: Locko Bank
A57: 56 | B57: AR-056 | C57: A | D57: trade-finance line | E57: EBRD | F57: Regional TFP: BCP Banque Centrale Populaire | G57: Morocco | H57: 2013 | I57: 3.602116e+08 | J57: EUR | K57: 478.4035 | L57: 38 | M57: Trade lines revolve: check whether the figure is a LIMIT (one commitment) or a running total of trade covered over the years. Our figure is EBRD's 'Net Cumulative Bank Investment'. | N57: =HYPERLINK("https://www.google.com/search?q=site%3Aebrd.com%2Fhome%2Fwork-with-us%2Fprojects%2Fpsd+Regional+TFP%3A+BCP+Banque+Centrale+Populaire","Search EBRD") | U57: https://www.ebrd.com/content/dam/ebrd_dxp/assets/pdfs/publications/ebrd-investments-1991-2025.xlsx | V57: 2013-06-03 | W57: Regional TFP: BCP Banque Centrale Populaire
A58: 57 | B58: AR-057 | C58: A | D58: trade-finance line | E58: EBRD | F58: Regional TFP: Kazkommertsbank (Guarantee & Pre-export) | G58: Kazakhstan | H58: 2000 | I58: 5.1330396e+08 | J58: EUR | K58: 474.09421 | L58: 39 | M58: Trade lines revolve: check whether the figure is a LIMIT (one commitment) or a running total of trade covered over the years. Our figure is EBRD's 'Net Cumulative Bank Investment'. | N58: =HYPERLINK("https://www.google.com/search?q=site%3Aebrd.com%2Fhome%2Fwork-with-us%2Fprojects%2Fpsd+Regional+TFP%3A+Kazkommertsbank+%28Guarantee+%26+Pre-export%29","Search EBRD") | U58: https://www.ebrd.com/content/dam/ebrd_dxp/assets/pdfs/publications/ebrd-investments-1991-2025.xlsx | V58: 2000-09-21 | W58: Regional TFP: Kazkommertsbank (Guarantee & Pre-export)
A59: 58 | B59: AR-058 | C59: A | D59: trade-finance line | E59: EBRD | F59: Regional TFP: Priorbank Guarantees and Pre-Export | G59: Belarus | H59: 2000 | I59: 5.1219315e+08 | J59: EUR | K59: 473.06825 | L59: 40 | M59: Trade lines revolve: check whether the figure is a LIMIT (one commitment) or a running total of trade covered over the years. Our figure is EBRD's 'Net Cumulative Bank Investment'. | N59: =HYPERLINK("https://www.google.com/search?q=site%3Aebrd.com%2Fhome%2Fwork-with-us%2Fprojects%2Fpsd+Regional+TFP%3A+Priorbank+Guarantees+and+Pre-Export","Search EBRD") | U59: https://www.ebrd.com/content/dam/ebrd_dxp/assets/pdfs/publications/ebrd-investments-1991-2025.xlsx | V59: 2000-01-14 | W59: Regional TFP: Priorbank Guarantees and Pre-Export
A60: 59 | B60: AR-059 | C60: A | D60: trade-finance line | E60: EBRD | F60: Regional TFP: Eurobank Ergasias S.A. | G60: Greece | H60: 2016 | I60: 4.1118018e+08 | J60: EUR | K60: 455.13657 | L60: 41 | M60: Trade lines revolve: check whether the figure is a LIMIT (one commitment) or a running total of trade covered over the years. Our figure is EBRD's 'Net Cumulative Bank Investment'. | N60: =HYPERLINK("https://www.google.com/search?q=site%3Aebrd.com%2Fhome%2Fwork-with-us%2Fprojects%2Fpsd+Regional+TFP%3A+Eurobank+Ergasias+S.A.","Search EBRD") | U60: https://www.ebrd.com/content/dam/ebrd_dxp/assets/pdfs/publications/ebrd-investments-1991-2025.xlsx | V60: 2016-07-22 | W60: Regional TFP: Eurobank Ergasias S.A.
A61: 60 | B61: AR-060 | C61: A | D61: trade-finance line | E61: EBRD | F61: Regional TFP: Komercijalna Banka | G61: North Macedonia | H61: 1999 | I61: 4.0809214e+08 | J61: EUR | K61: 434.9348 | L61: 42 | M61: Trade lines revolve: check whether the figure is a LIMIT (one commitment) or a running total of trade covered over the years. Our figure is EBRD's 'Net Cumulative Bank Investment'. | N61: =HYPERLINK("https://www.google.com/search?q=site%3Aebrd.com%2Fhome%2Fwork-with-us%2Fprojects%2Fpsd+Regional+TFP%3A+Komercijalna+Banka","Search EBRD") | U61: https://www.ebrd.com/content/dam/ebrd_dxp/assets/pdfs/publications/ebrd-investments-1991-2025.xlsx | V61: 1999-06-22 | W61: Regional TFP: Komercijalna Banka
A62: 61 | B62: AR-061 | C62: A | D62: trade-finance line | E62: EBRD | F62: Regional TFP: UBCI | G62: Tunisia | H62: 2018 | I62: 3.6185912e+08 | J62: EUR | K62: 427.33933 | L62: 43 | M62: Trade lines revolve: check whether the figure is a LIMIT (one commitment) or a running total of trade covered over the years. Our figure is EBRD's 'Net Cumulative Bank Investment'. | N62: =HYPERLINK("https://www.google.com/search?q=site%3Aebrd.com%2Fhome%2Fwork-with-us%2Fprojects%2Fpsd+Regional+TFP%3A+UBCI","Search EBRD") | U62: https://www.ebrd.com/content/dam/ebrd_dxp/assets/pdfs/publications/ebrd-investments-1991-2025.xlsx | V62: 2018-02-19 | W62: Regional TFP: UBCI
A63: 62 | B63: AR-062 | C63: A | D63: trade-finance line | E63: EBRD | F63: Regional TFP: Denizbank | G63: Türkiye | H63: 2020 | I63: 3.6252759e+08 | J63: EUR | K63: 414.07756 | L63: 44 | M63: Trade lines revolve: check whether the figure is a LIMIT (one commitment) or a running total of trade covered over the years. Our figure is EBRD's 'Net Cumulative Bank Investment'. | N63: =HYPERLINK("https://www.google.com/search?q=site%3Aebrd.com%2Fhome%2Fwork-with-us%2Fprojects%2Fpsd+Regional+TFP%3A+Denizbank","Search EBRD") | U63: https://www.ebrd.com/content/dam/ebrd_dxp/assets/pdfs/publications/ebrd-investments-1991-2025.xlsx | V63: 2020-08-12 | W63: Regional TFP: Denizbank
A64: 63 | B64: AR-063 | C64: A | D64: trade-finance line | E64: IFC | F64: GTLP CITI V Increment | G64: Regional — Global | I64: 400000000 | J64: USD | K64: 400 | L64: 35 | M64: Trade lines revolve: check whether the figure is a LIMIT (one commitment) or a running total of trade covered over the years. | N64: =HYPERLINK("https://disclosures.ifc.org/project-detail/SII/47185/gtlp-citi-v-increment","Open page") | U64: https://disclosures.ifc.org/project-detail/SII/47185/gtlp-citi-v-increment | W64: GTLP CITI V Increment
A65: 64 | B65: AR-064 | C65: A | D65: trade-finance line | E65: IFC | F65: IDA PSW GTFP LE | G65: Regional — Global | H65: 2023 | I65: 400000000 | J65: USD | K65: 400 | L65: 39 | M65: Trade lines revolve: check whether the figure is a LIMIT (one commitment) or a running total of trade covered over the years. | N65: =HYPERLINK("https://disclosures.ifc.org/project-detail/SII/48217/ida-psw-gtfp-le","Open page") | U65: https://disclosures.ifc.org/project-detail/SII/48217/ida-psw-gtfp-le | V65: 2023-05-12 | W65: IDA PSW GTFP LE
A66: 65 | B66: AR-065 | C66: A | D66: trade-finance line | E66: EBRD | F66: Regional TFP: Khan Bank | G66: Mongolia | H66: 2007 | I66: 2.8977059e+08 | J66: EUR | K66: 397.12422 | L66: 46 | M66: Trade lines revolve: check whether the figure is a LIMIT (one commitment) or a running total of trade covered over the years. Our figure is EBRD's 'Net Cumulative Bank Investment'. | N66: =HYPERLINK("https://www.google.com/search?q=site%3Aebrd.com%2Fhome%2Fwork-with-us%2Fprojects%2Fpsd+Regional+TFP%3A+Khan+Bank","Search EBRD") | U66: https://www.ebrd.com/content/dam/ebrd_dxp/assets/pdfs/publications/ebrd-investments-1991-2025.xlsx | V66: 2007-10-30 | W66: Regional TFP: Khan Bank
A67: 66 | B67: AR-066 | C67: B | D67: top 200 by USD | E67: AfDB | F67: South Africa - Medupi Power Project | G67: South Africa | H67: 2009 | I67: 1.2544771e+09 | J67: XDR | K67: 1940.9683 | L67: 1 | N67: =HYPERLINK("https://mapafrica.afdb.org/en/projects/46002-P-ZA-FAA-001","Open page") | U67: https://mapafrica.afdb.org/en/projects/46002-P-ZA-FAA-001 | V67: 2009-11-25 | W67: South Africa - Medupi Power Project
A68: 67 | B68: AR-067 | C68: B | D68: top 200 by USD | E68: DFC | F68: Redacted | G68: Undisclosed | H68: 2024 | I68: 1715000000 | J68: USD | K68: 1715 | L68: 1 | M68: DFC withheld the name; there is no public page. | N68: No link | U68: Redacted | W68: Redacted
A69: 68 | B69: AR-068 | C69: B | D69: top 200 by USD | E69: AfDB | F69: Botswana - The Economic Diversification Support Programme | G69: Botswana | H69: 2009 | I69: 1.0883051e+09 | J69: XDR | K69: 1683.8615 | L69: 2 | N69: =HYPERLINK("https://mapafrica.afdb.org/en/projects/46002-P-BW-K00-001","Open page") | U69: https://mapafrica.afdb.org/en/projects/46002-P-BW-K00-001 | V69: 2009-06-02 | W69: Botswana - The Economic Diversification Support Programme
A70: 69 | B70: AR-069 | C70: B | D70: top 200 by USD | E70: AfDB | F70: Transition Support Facility – ADF-16 Allocation | G70: Regional — Africa | H70: 2023 | I70: 1244280000 | J70: XDR | K70: 1656.0185 | L70: 3 | N70: =HYPERLINK("https://mapafrica.afdb.org/en/projects/46002-P-Z1-K00-188","Open page") | U70: https://mapafrica.afdb.org/en/projects/46002-P-Z1-K00-188 | V70: 2023-05-16 | W70: Transition Support Facility – ADF-16 Allocation
A71: 70 | B71: AR-070 | C71: B | D71: top 200 by USD | E71: DFC | F71: Rovuma LNG Phase I | G71: Mozambique | H71: 2022 | I71: 1500000000 | J71: USD | K71: 1500 | L71: 2 | N71: =HYPERLINK("https://www.dfc.gov/sites/default/files/media/documents/9000093392.pdf","Open page") | U71: https://www.dfc.gov/sites/default/files/media/documents/9000093392.pdf | W71: Rovuma LNG Phase I
A72: 71 | B72: AR-071 | C72: B | D72: top 200 by USD | E72: AfDB | F72: Multinational - Transition support fund ADF- 15 Allocation | G72: Regional — Africa | H72: 2020 | I72: 899400000 | J72: XDR | K72: 1257.1561 | L72: 4 | N72: =HYPERLINK("https://mapafrica.afdb.org/en/projects/46002-P-Z1-K00-167","Open page") | U72: https://mapafrica.afdb.org/en/projects/46002-P-Z1-K00-167 | V72: 2020-06-10 | W72: Multinational - Transition support fund ADF- 15 Allocation
A73: 72 | B73: AR-072 | C73: B | D73: top 200 by USD | E73: AfDB | F73: Multinational - Fragile states fund allocation ADF-12 | G73: Regional — Africa | H73: 2010 | I73: 764000000 | J73: XDR | K73: 1156.9794 | L73: 5 | N73: =HYPERLINK("https://mapafrica.afdb.org/en/projects/46002-P-Z1-K00-046","Open page") | U73: https://mapafrica.afdb.org/en/projects/46002-P-Z1-K00-046 | V73: 2010-11-09 | W73: Multinational - Fragile states fund allocation ADF-12
A74: 73 | B74: AR-073 | C74: B | D74: top 200 by USD | E74: AfDB | F74: Angola - Power Sector Reform Support Program | G74: Angola | H74: 2014 | I74: 7.2885235e+08 | J74: XDR | K74: 1101.4176 | L74: 6 | N74: =HYPERLINK("https://mapafrica.afdb.org/en/projects/46002-P-AO-FA0-002","Open page") | U74: https://mapafrica.afdb.org/en/projects/46002-P-AO-FA0-002 | V74: 2014-05-13 | W74: Angola - Power Sector Reform Support Program
A75: 74 | B75: AR-074 | C75: B | D75: top 200 by USD | E75: AfDB | F75: Algeria - Industrial and Energy Competitiveness Support Programme (PACIE) | G75: Algeria | H75: 2016 | I75: 7.6395491e+08 | J75: XDR | K75: 1060.1288 | L75: 7 | N75: =HYPERLINK("https://mapafrica.afdb.org/en/projects/46002-P-DZ-K00-007","Open page") | U75: https://mapafrica.afdb.org/en/projects/46002-P-DZ-K00-007 | V75: 2016-11-02 | W75: Algeria - Industrial and Energy Competitiveness Support Programme (PACIE)
A76: 75 | B76: AR-075 | C76: B | D76: top 200 by USD | E76: AfDB | F76: South Africa -Transnet III | G76: South Africa | H76: 2024 | I76: 7.8930371e+08 | J76: XDR | K76: 1048.6973 | L76: 8 | N76: =HYPERLINK("https://mapafrica.afdb.org/en/projects/46002-P-ZA-DC0-003","Open page") | U76: https://mapafrica.afdb.org/en/projects/46002-P-ZA-DC0-003 | V76: 2024-07-12 | W76: South Africa -Transnet III
A77: 76 | B77: AR-076 | C77: B | D77: top 200 by USD | E77: EIB Global | F77: ISTANBUL URBAN TRANSPORT II | G77: Türkiye | H77: 2008 | I77: 700000000 | J77: EUR | K77: 1029.5285 | L77: 1 | N77: =HYPERLINK("https://www.eib.org/en/projects/loans/all/20060462","Open page") | U77: https://www.eib.org/en/projects/loans/all/20060462 | V77: 2008-04-10 | W77: ISTANBUL URBAN TRANSPORT II
A78: 77 | B78: AR-077 | C78: B | D78: top 200 by USD | E78: AfDB | F78: Multinational - Transition support Fund ADF-13 allocation | G78: Regional — Africa | H78: 2013 | I78: 662000000 | J78: XDR | K78: 1005.8799 | L78: 9 | N78: =HYPERLINK("https://mapafrica.afdb.org/en/projects/46002-P-Z1-K00-078","Open page") | U78: https://mapafrica.afdb.org/en/projects/46002-P-Z1-K00-078 | V78: 2013-11-13 | W78: Multinational - Transition support Fund ADF-13 allocation
A79: 78 | B79: AR-078 | C79: B | D79: top 200 by USD | E79: DFC | F79: Gavi Alliance | G79: Regional — Global | H79: 2024 | I79: 1000000000 | J79: USD | K79: 1000 | L79: 3 | N79: =HYPERLINK("https://www.dfc.gov/sites/default/files/media/documents/9000116518.pdf","Open page") | U79: https://www.dfc.gov/sites/default/files/media/documents/9000116518.pdf | W79: Gavi Alliance
A80: 79 | B80: AR-079 | C80: B | D80: top 200 by USD | E80: DFC | F80: Debt Conversion for Water Security and Climate Resilience in the Rio Lempa Watershed | G80: El Salvador | H80: 2024 | I80: 1000000000 | J80: USD | K80: 1000 | L80: 4 | N80: =HYPERLINK("https://www.dfc.gov/sites/default/files/media/documents/9000116724.pdf","Open page") | U80: https://www.dfc.gov/sites/default/files/media/documents/9000116724.pdf | W80: Debt Conversion for Water Security and Climate Resilience in the Rio Lempa Watershed
A81: 80 | B81: AR-080 | C81: B | D81: top 200 by USD | E81: AfDB | F81: Multinational - Transition Support Fund - ADF-14 Allocation | G81: Regional — Africa | H81: 2017 | I81: 711150000 | J81: XDR | K81: 989.82551 | L81: 10 | N81: =HYPERLINK("https://mapafrica.afdb.org/en/projects/46002-P-Z1-K00-119","Open page") | U81: https://mapafrica.afdb.org/en/projects/46002-P-Z1-K00-119 | V81: 2017-02-08 | W81: Multinational - Transition Support Fund - ADF-14 Allocation
A82: 81 | B82: AR-081 | C82: B | D82: top 200 by USD | E82: EIB Global | F82: NBE LOAN FOR SMES AND MIDCAPS COVID-19 | G82: Egypt | H82: 2020 | I82: 800000000 | J82: EUR | K82: 913.7568 | L82: 2 | N82: =HYPERLINK("https://www.eib.org/en/projects/loans/all/20200093","Open page") | U82: https://www.eib.org/en/projects/loans/all/20200093 | V82: 2020-09-02 | W82: NBE LOAN FOR SMES AND MIDCAPS COVID-19
A83: 82 | B83: AR-082 | C83: B | D83: top 200 by USD | E83: AfDB | F83: Algeria - Laghouat – Ghardaïa – El Menéa Railway Line Construction Project | G83: Algeria | H83: 2025 | I83: 6.3950963e+08 | J83: XDR | K83: 868.25519 | L83: 11 | N83: =HYPERLINK("https://mapafrica.afdb.org/en/projects/46002-P-DZ-DC0-003","Open page") | U83: https://mapafrica.afdb.org/en/projects/46002-P-DZ-DC0-003 | V83: 2025-12-11 | W83: Algeria - Laghouat – Ghardaïa – El Menéa Railway Line Construction Project
A84: 83 | B84: AR-083 | C84: B | D84: top 200 by USD | E84: EBRD | F84: Roads Reconstruction and Upgrading Project | G84: Azerbaijan | H84: 2011 | I84: 5.9298131e+08 | J84: EUR | K84: 825.40331 | L84: 16 | M84: Our figure is EBRD's 'Net Cumulative Bank Investment'. | N84: =HYPERLINK("https://www.google.com/search?q=site%3Aebrd.com%2Fhome%2Fwork-with-us%2Fprojects%2Fpsd+Roads+Reconstruction+and+Upgrading+Project","Search EBRD") | U84: https://www.ebrd.com/content/dam/ebrd_dxp/assets/pdfs/publications/ebrd-investments-1991-2025.xlsx | V84: 2011-12-15 | W84: Roads Reconstruction and Upgrading Project
A85: 84 | B85: AR-084 | C85: B | D85: top 200 by USD | E85: AfDB | F85: Mozambique - Mozambique LNG Area 1 | G85: Mozambique | H85: 2019 | I85: 5.9021331e+08 | J85: XDR | K85: 815.18491 | L85: 12 | N85: =HYPERLINK("https://mapafrica.afdb.org/en/projects/46002-P-MZ-FD0-003","Open page") | U85: https://mapafrica.afdb.org/en/projects/46002-P-MZ-FD0-003 | V85: 2019-11-21 | W85: Mozambique - Mozambique LNG Area 1
A86: 85 | B86: AR-085 | C86: B | D86: top 200 by USD | E86: DFC | F86: Redacted | G86: Undisclosed | H86: 2023 | I86: 8.1458491e+08 | J86: USD | K86: 814.58491 | L86: 5 | M86: DFC withheld the name; there is no public page. | N86: No link | U86: Redacted | W86: Redacted
A87: 86 | B87: AR-086 | C87: B | D87: top 200 by USD | E87: EBRD | F87: Factoring - National Bank of Greece | G87: Greece | H87: 2019 | I87: 725000000 | J87: EUR | K87: 811.61937 | L87: 17 | M87: Our figure is EBRD's 'Net Cumulative Bank Investment'. | N87: =HYPERLINK("https://www.google.com/search?q=site%3Aebrd.com%2Fhome%2Fwork-with-us%2Fprojects%2Fpsd+Factoring+-+National+Bank+of+Greece","Search EBRD") | U87: https://www.ebrd.com/content/dam/ebrd_dxp/assets/pdfs/publications/ebrd-investments-1991-2025.xlsx | V87: 2019-12-19 | W87: Factoring - National Bank of Greece
A88: 87 | B88: AR-087 | C88: B | D88: top 200 by USD | E88: AfDB | F88: Tanzania - Tanzania/Burundi/DR Congo Joint Standard Gauge Railway Project Phase II | G88: Regional — Africa | H88: 2023 | I88: 5.9041026e+08 | J88: XDR | K88: 785.77997 | L88: 13 | N88: =HYPERLINK("https://mapafrica.afdb.org/en/projects/46002-P-Z1-DC0-041","Open page") | U88: https://mapafrica.afdb.org/en/projects/46002-P-Z1-DC0-041 | V88: 2023-12-08 | W88: Tanzania - Tanzania/Burundi/DR Congo Joint Standard Gauge Railway Project Phase II
A89: 88 | B89: AR-088 | C89: B | D89: top 200 by USD | E89: BII | F89: Actis Infrastructure 2 LP | G89: Regional — Global | H89: 2007 | I89: 750000000 | J89: USD | K89: 750 | L89: 1 | N89: =HYPERLINK("https://d-portal.org/q.html?aid=GB-COH-03877777-F209601-01","Open page") | U89: https://d-portal.org/q.html?aid=GB-COH-03877777-F209601-01 | V89: 2007-09-14 | W89: Actis Infrastructure 2 LP
A90: 89 | B90: AR-089 | C90: B | D90: top 200 by USD | E90: DFC | F90: Islamic Republic of Pakistan | G90: Pakistan | H90: 2004 | I90: 7.4884535e+08 | J90: USD | K90: 748.84535 | L90: 6 | N90: =HYPERLINK("https://www.dfc.gov/sites/default/files/media/documents/FY24%20DFC%20Annual%20Project%20Data_508.xlsx","Open page") | U90: https://www.dfc.gov/sites/default/files/media/documents/FY24%20DFC%20Annual%20Project%20Data_508.xlsx | W90: Islamic Republic of Pakistan
A91: 90 | B91: AR-090 | C91: B | D91: top 200 by USD | E91: DFC | F91: Blue Bonds for Marine Conservation - Gabon | G91: Gabon | H91: 2023 | I91: 747789905 | J91: USD | K91: 747.7899 | L91: 7 | N91: =HYPERLINK("https://www.dfc.gov/sites/default/files/media/documents/9000093576.pdf","Open page") | U91: https://www.dfc.gov/sites/default/files/media/documents/9000093576.pdf | W91: Blue Bonds for Marine Conservation - Gabon
A92: 91 | B92: AR-091 | C92: B | D92: top 200 by USD | E92: ADB | F92: Railways Track Electrification Project | G92: India | H92: 2018 | I92: 50400000000 | J92: INR | K92: 746.20869 | L92: 2 | M92: Loaded in rupees; the description says 'up to $750 million'. | N92: =HYPERLINK("https://www.adb.org/projects/51228-001/main","Open page") | U92: https://www.adb.org/projects/51228-001/main | V92: 2018-07-10 | W92: Railways Track Electrification Project
A93: 92 | B93: AR-092 | C93: B | D93: top 200 by USD | E93: EIB Global | F93: EGYPT GRID MODERNIZATION AND EXPANSION | G93: Egypt | H93: 2026 | I93: 600000000 | J93: EUR | K93: 697.9782 | L93: 3 | N93: =HYPERLINK("https://www.eib.org/en/projects/loans/all/20250265","Open page") | U93: https://www.eib.org/en/projects/loans/all/20250265 | V93: 2026-06-23 | W93: EGYPT GRID MODERNIZATION AND EXPANSION
A94: 93 | B94: AR-093 | C94: B | D94: top 200 by USD | E94: EIB Global | F94: BRAZIL CLIMATE CHANGE MITIGATION FL | G94: Brazil | H94: 2011 | I94: 500000000 | J94: EUR | K94: 695.9775 | L94: 4 | N94: =HYPERLINK("https://www.eib.org/en/projects/loans/all/20070360","Open page") | U94: https://www.eib.org/en/projects/loans/all/20070360 | V94: 2011-10-04 | W94: BRAZIL CLIMATE CHANGE MITIGATION FL
A95: 94 | B95: AR-094 | C95: B | D95: top 200 by USD | E95: EIB Global | F95: URBAN TRANSPORT INFRASTRUCTURE FRAMEWORK EGYPT | G95: Egypt | H95: 2020 | I95: 600000000 | J95: EUR | K95: 685.3176 | L95: 5 | N95: =HYPERLINK("https://www.eib.org/en/projects/loans/all/20200144","Open page") | U95: https://www.eib.org/en/projects/loans/all/20200144 | V95: 2020-12-16 | W95: URBAN TRANSPORT INFRASTRUCTURE FRAMEWORK EGYPT
A96: 95 | B96: AR-095 | C96: B | D96: top 200 by USD | E96: EIB Global | F96: CHINA CLIMATE CHANGE FRAMEWORK LOAN | G96: China | H96: 2007 | I96: 500000000 | J96: EUR | K96: 685.239 | L96: 6 | N96: =HYPERLINK("https://www.eib.org/en/projects/loans/all/20060086","Open page") | U96: https://www.eib.org/en/projects/loans/all/20060086 | V96: 2007-11-27 | W96: CHINA CLIMATE CHANGE FRAMEWORK LOAN
A97: 96 | B97: AR-096 | C97: B | D97: top 200 by USD | E97: DFC | F97: Marine Conservation in the Galapagos Islands | G97: Ecuador | H97: 2022 | I97: 6.8379633e+08 | J97: USD | K97: 683.79633 | L97: 8 | N97: =HYPERLINK("https://www.dfc.gov/sites/default/files/media/documents/9000104959_0.pdf","Open page") | U97: https://www.dfc.gov/sites/default/files/media/documents/9000104959_0.pdf | W97: Marine Conservation in the Galapagos Islands
A98: 97 | B98: AR-097 | C98: B | D98: top 200 by USD | E98: AfDB | F98: Egypt - Financial Sector Reform Programme (FRSP-1) | G98: Egypt | H98: 2006 | I98: 4.5436689e+08 | J98: XDR | K98: 670.38109 | L98: 14 | N98: =HYPERLINK("https://mapafrica.afdb.org/en/projects/46002-P-EG-HZ0-001","Open page") | U98: https://mapafrica.afdb.org/en/projects/46002-P-EG-HZ0-001 | V98: 2006-07-26 | W98: Egypt - Financial Sector Reform Programme (FRSP-1)
A99: 98 | B99: AR-098 | C99: B | D99: top 200 by USD | E99: EIB Global | F99: MEDGAZ PIPELINE | G99: Algeria | H99: 2010 | I99: 500000000 | J99: EUR | K99: 662.8585 | L99: 7 | N99: =HYPERLINK("https://www.eib.org/en/projects/loans/all/20080163","Open page") | U99: https://www.eib.org/en/projects/loans/all/20080163 | V99: 2010-11-22 | W99: MEDGAZ PIPELINE
A100: 99 | B100: AR-099 | C100: B | D100: top 200 by USD | E100: AfDB | F100: Multinational (Cameroon - Nigeria) - Transport Facilitation Program Corridor - Bamenda-Enugu- (PAGODA Supplemental Grant) | G100: Regional — Africa | H100: 2008 | I100: 4.1381208e+08 | J100: XDR | K100: 654.25344 | L100: 15 | N100: =HYPERLINK("https://mapafrica.afdb.org/en/projects/46002-P-Z1-DB0-023","Open page") | U100: https://mapafrica.afdb.org/en/projects/46002-P-Z1-DB0-023 | V100: 2008-11-25 | W100: Multinational (Cameroon - Nigeria) - Transport Facilitation Program Corridor - Bamenda-Enugu- (PAGODA Supplemental Grant)
...

Sheet Institution guide
A1: Institution | B1: Where the amount is | C1: Differences that are NORMAL here | D1: Page layout checked 24 Sep 2026?
A2: IFC | B2: Open the link. Click the section 'Total Project Cost and Amount and Nature of IFC's Investment'. It gives the total project and IFC's own investment separately; compare OUR amount with IFC's investment. | C2: Loan plus equity may be listed separately; add them. 'Up to' figures are fine. | D2: Yes
A3: EBRD | B3: There is no page per record: the link is a web search. Open the result whose address contains '/projects/psd/'. That is the Project Summary Document; its financing section states EBRD's own amount. | C3: Our figure is EBRD's 'Net Cumulative Bank Investment' from its portfolio list, not the signing amount, so it can differ from the PSD. A much LARGER figure than the PSD is exactly what to look for. | D3: Search only; PSD layout not checked
A4: EIB Global | B4: Open the link and click 'Signature(s)'. It lists the signed amount and each signature date. | C4: EIB publishes loan tranches, so one project can be several of our records. Match OUR amount to one signature line, not the project total. | D4: Yes
A5: AfDB | B5: Open the link and read 'Commitment (UA)' on Overview. Then click 'Financial information': under 'Commitments by source' note the African Development Bank Group line. | C5: Amounts are in UA (Units of Account, the IMF's SDR). Record UA figures, not USD. If 'Commitments by source' shows other financiers, OUR figure may include them — say so in Notes. | D5: Yes
A6: IDB Invest | B6: Open the link. 'Investment summary' shows 'FINANCING AMOUNT'. | C6: The page can show the whole IDB Group's figure, typically 1.8 to 5.3 times IDB Invest's own share, which is what we load. A LARGER page figure is expected; a SMALLER one is a problem. | D6: Yes
A7: FMO | B7: Open the link. Read 'Total FMO financing' in the side panel. | C7: 'Funding' says whose money it was: 'FMO NV' is FMO's own account; anything else is a government fund FMO manages. | D7: Yes
A8: DFC | B8: The link is a PDF project summary. Look for the proposed DFC financing amount. | C8: Records named 'Redacted' have no public page: mark 'Can't verify'. | D8: No
A9: ADB | B9: Open the link (your browser may show a security check first). Look for the financing table, ADB's own line. | C9: One ADB record is in Indian rupees; its description says 'up to $750 million'. | D9: No - the site blocked automated checking
A10: BII | B10: The link opens d-portal (the IATI data viewer). Look at the commitment transactions for this activity. | C10: BII publishes transactions, so one deal can be several records. | D10: No
A11: Proparco | B11: Open the link (French). Look for 'Montant' / the amount of Proparco's financing. Records loaded from AFD's open data have no page of their own: the link is a web search instead. | C11: Amounts are in EUR. | D11: No

Sheet Progress
A1: Progress
B3: All | C3: A | D3: B | E3: C
A4: Records in the queue | B4: =COUNTA(Queue!$B$2:$B$214) | C4: =COUNTIF(Queue!$C$2:$C$214,"A") | D4: =COUNTIF(Queue!$C$2:$C$214,"B") | E4: =COUNTIF(Queue!$C$2:$C$214,"C")
A5: Reviewed (any verdict) | B5: =COUNTA(Queue!$O$2:$O$214) | C5: =COUNTIFS(Queue!$C$2:$C$214,"A",Queue!$O$2:$O$214,"<>") | D5: =COUNTIFS(Queue!$C$2:$C$214,"B",Queue!$O$2:$O$214,"<>") | E5: =COUNTIFS(Queue!$C$2:$C$214,"C",Queue!$O$2:$O$214,"<>")
A6: Correct - matches the page | B6: =COUNTIF(Queue!$O$2:$O$214,$A6) | C6: =COUNTIFS(Queue!$C$2:$C$214,"A",Queue!$O$2:$O$214,$A6) | D6: =COUNTIFS(Queue!$C$2:$C$214,"B",Queue!$O$2:$O$214,$A6) | E6: =COUNTIFS(Queue!$C$2:$C$214,"C",Queue!$O$2:$O$214,$A6)
A7: Correct - small difference (rounding or exchange rate) | B7: =COUNTIF(Queue!$O$2:$O$214,$A7) | C7: =COUNTIFS(Queue!$C$2:$C$214,"A",Queue!$O$2:$O$214,$A7) | D7: =COUNTIFS(Queue!$C$2:$C$214,"B",Queue!$O$2:$O$214,$A7) | E7: =COUNTIFS(Queue!$C$2:$C$214,"C",Queue!$O$2:$O$214,$A7)
A8: Wrong - programme or envelope total, not this deal | B8: =COUNTIF(Queue!$O$2:$O$214,$A8) | C8: =COUNTIFS(Queue!$C$2:$C$214,"A",Queue!$O$2:$O$214,$A8) | D8: =COUNTIFS(Queue!$C$2:$C$214,"B",Queue!$O$2:$O$214,$A8) | E8: =COUNTIFS(Queue!$C$2:$C$214,"C",Queue!$O$2:$O$214,$A8)
A9: Wrong - total project cost, not this institution's share | B9: =COUNTIF(Queue!$O$2:$O$214,$A9) | C9: =COUNTIFS(Queue!$C$2:$C$214,"A",Queue!$O$2:$O$214,$A9) | D9: =COUNTIFS(Queue!$C$2:$C$214,"B",Queue!$O$2:$O$214,$A9) | E9: =COUNTIFS(Queue!$C$2:$C$214,"C",Queue!$O$2:$O$214,$A9)
A10: Wrong - cumulative or revolving total, not one commitment | B10: =COUNTIF(Queue!$O$2:$O$214,$A10) | C10: =COUNTIFS(Queue!$C$2:$C$214,"A",Queue!$O$2:$O$214,$A10) | D10: =COUNTIFS(Queue!$C$2:$C$214,"B",Queue!$O$2:$O$214,$A10) | E10: =COUNTIFS(Queue!$C$2:$C$214,"C",Queue!$O$2:$O$214,$A10)
A11: Wrong - currency or units | B11: =COUNTIF(Queue!$O$2:$O$214,$A11) | C11: =COUNTIFS(Queue!$C$2:$C$214,"A",Queue!$O$2:$O$214,$A11) | D11: =COUNTIFS(Queue!$C$2:$C$214,"B",Queue!$O$2:$O$214,$A11) | E11: =COUNTIFS(Queue!$C$2:$C$214,"C",Queue!$O$2:$O$214,$A11)
A12: Wrong - other (explain in Notes) | B12: =COUNTIF(Queue!$O$2:$O$214,$A12) | C12: =COUNTIFS(Queue!$C$2:$C$214,"A",Queue!$O$2:$O$214,$A12) | D12: =COUNTIFS(Queue!$C$2:$C$214,"B",Queue!$O$2:$O$214,$A12) | E12: =COUNTIFS(Queue!$C$2:$C$214,"C",Queue!$O$2:$O$214,$A12)
A13: Can't verify - no link, page gone, or no amount shown | B13: =COUNTIF(Queue!$O$2:$O$214,$A13) | C13: =COUNTIFS(Queue!$C$2:$C$214,"A",Queue!$O$2:$O$214,$A13) | D13: =COUNTIFS(Queue!$C$2:$C$214,"B",Queue!$O$2:$O$214,$A13) | E13: =COUNTIFS(Queue!$C$2:$C$214,"C",Queue!$O$2:$O$214,$A13)
A14: Unsure - discuss | B14: =COUNTIF(Queue!$O$2:$O$214,$A14) | C14: =COUNTIFS(Queue!$C$2:$C$214,"A",Queue!$O$2:$O$214,$A14) | D14: =COUNTIFS(Queue!$C$2:$C$214,"B",Queue!$O$2:$O$214,$A14) | E14: =COUNTIFS(Queue!$C$2:$C$214,"C",Queue!$O$2:$O$214,$A14)
A15: Still to do | B15: =B4-B5 | C15: =C4-C5 | D15: =D4-D5 | E15: =E4-E5
A17: Counts update as you fill the Verdict column. 'Reviewed' counts any row with a verdict.

Sheet Lists
A1: Correct - matches the page
A2: Correct - small difference (rounding or exchange rate)
A3: Wrong - programme or envelope total, not this deal
A4: Wrong - total project cost, not this institution's share
A5: Wrong - cumulative or revolving total, not one commitment
A6: Wrong - currency or units
A7: Wrong - other (explain in Notes)
A8: Can't verify - no link, page gone, or no amount shown
A9: Unsure - discuss
